structured_array/__init__.py
structured_array/_normalize.py
structured_array/array.py
structured_array/core.py
structured_array/groupby.py
structured_array/typing.py
structured_array/expression/__init__.py
structured_array/expression/_array.py
structured_array/expression/_char.py
structured_array/expression/_expr.py
structured_array/expression/_namespace.py
structured_array/expression/_unitexpr.py
structured_array/testing/__init__.py
structured_array/testing/_compare.py
structured_array-0.0.1.dist-info/METADATA
structured_array-0.0.1.dist-info/WHEEL
structured_array-0.0.1.dist-info/licenses/LICENSE
structured_array-0.0.1.dist-info/RECORD
