Metadata-Version: 2.3
Name: structured-array
Version: 0.0.1
Summary: Efficient manipulation of the numpy structured arrays.
Project-URL: Documentation, https://github.com/Hanjin Liu/structured-array#readme
Project-URL: Issues, https://github.com/Hanjin Liu/structured-array/issues
Project-URL: Source, https://github.com/Hanjin Liu/structured-array
Author-email: Hanjin Liu <liuhanjin-sc@i.softbank.jp>
License: MIT License
License-File: LICENSE
Classifier: Development Status :: 4 - Beta
Classifier: Programming Language :: Python
Classifier: Programming Language :: Python :: 3.9
Classifier: Programming Language :: Python :: 3.10
Classifier: Programming Language :: Python :: 3.11
Classifier: Programming Language :: Python :: 3.12
Classifier: Programming Language :: Python :: 3.13
Classifier: Programming Language :: Python :: Implementation :: CPython
Classifier: Programming Language :: Python :: Implementation :: PyPy
Requires-Python: >=3.9
Requires-Dist: numpy>=1.21.0
Requires-Dist: tabulate>=0.9.0
Provides-Extra: testing
Requires-Dist: pandas>=2.2.3; extra == 'testing'
Requires-Dist: polars>=1.9.0; extra == 'testing'
Requires-Dist: pytest; extra == 'testing'
Requires-Dist: pytest-cov; extra == 'testing'
